LICENSE
README.md
setup.cfg
setup.py
threej/__init__.py
threej/numba.py
threej.egg-info/PKG-INFO
threej.egg-info/SOURCES.txt
threej.egg-info/dependency_links.txt
threej.egg-info/entry_points.txt
threej.egg-info/requires.txt
threej.egg-info/top_level.txt
threej/test/__init__.py
threej/test/test_threej.py