Metadata-Version: 2.1
Name: threej
Version: 2022.4.1
Summary: Package for Wigner 3j symbols in pure Python with Numba support
Home-page: https://github.com/ntessore/threej
Author: Nicolas Tessore
Author-email: n.tessore@ucl.ac.uk
License: MIT
Platform: UNKNOWN
Classifier: Programming Language :: Python :: 3
Classifier: License :: OSI Approved :: MIT License
Classifier: Operating System :: OS Independent
Requires-Python: >=3.6
Provides-Extra: numba
License-File: LICENSE
